setup.py
PicDB/__init__.py
PicDB.egg-info/PKG-INFO
PicDB.egg-info/SOURCES.txt
PicDB.egg-info/dependency_links.txt
PicDB.egg-info/not-zip-safe
PicDB.egg-info/top_level.txt