Metadata-Version: 1.0
Name: PicDB
Version: 1.1
Summary: DataBase in picture!?!?!??!?!!!
Home-page: UNKNOWN
Author: UNKNOWN
Author-email: ma_mush@mail.ru
License: UNKNOWN
Platform: UNKNOWN
